pims_api_client/__init__.py
pims_api_client/api.py
pims_api_client/client.py
pims_api_client/configurator.py
pims_api_client/exceptions.py
pims_api_client/methods/__init__.py
pims_api_client/methods/attributes.py
pims_api_client/methods/base_executor.py
pims_api_client/methods/products.py
pims_api_client/schemas/__init__.py
pims_api_client/schemas/attributes.py
pims_api_client/schemas/base.py
pims_api_client/schemas/products.py
pims_api_client-0.1.7.dist-info/WHEEL
pims_api_client-0.1.7.dist-info/METADATA
pims_api_client-0.1.7.dist-info/RECORD
