Metadata-Version: 2.1
Name: pims-api-client
Version: 0.1.7
Summary: INLB PIMS API Client
Home-page: https://gitlab.inlb.ru/inlb/python/pims-api-client
License: MIT
Keywords: pims,api_client
Author: Никита Злаин
Author-email: nz@inlb.ru
Requires-Python: >=3.9,<4.0
Classifier: License :: OSI Approved :: MIT License
Classifier: Programming Language :: Python :: 3
Classifier: Programming Language :: Python :: 3.10
Classifier: Programming Language :: Python :: 3.9
Requires-Dist: httpx (>=0.22.0,<0.23.0)
Requires-Dist: pydantic (>=1.9,<2.0)
Requires-Dist: pyhumps (>=3.5.3,<4.0.0)
Requires-Dist: pytest-asyncio (>=0.18.2,<0.19.0)
Project-URL: Repository, https://gitlab.inlb.ru/inlb/python/pims-api-client
